evaluationmetric/__init__.py
evaluationmetric-0.1.1.dist-info/METADATA
evaluationmetric-0.1.1.dist-info/WHEEL
evaluationmetric-0.1.1.dist-info/top_level.txt
evaluationmetric-0.1.1.dist-info/RECORD
